Workbook

Sheet Premissas
B2: CASE: SIMPLES HÍBRIDO — Distribuidor / Atacadista
B3: Impacto da Reforma Tributária (LC 214/2025) na transferência de crédito de IBS/CBS
B5: 1. PERFIL DA EMPRESA (Atacadista optante do Simples — Anexo I / Comércio)
B7: Faturamento mensal | C7: 300000 | E7: Receita bruta mensal informada
B8: Faturamento anual (RBT12) | C8: =C7*12 -> 3600000 | E8: Base para faixa do Simples
B9: % vendas p/ Lucro Real (B2B que credita) | C9: 0.8 | E9: Clientes que precisam de crédito
B10: % vendas p/ consumidor final / não credita | C10: 0.2 | E10: Não sofrem com perda de crédito
B11: Margem bruta média | C11: 0.15 | E11: Margem média (cenário escolhido)
B13: 2. ESTRUTURA DE CUSTOS E DESPESAS MENSAIS (dados fictícios)
B15: CMV — compras de mercadorias (tributadas) | C15: =C16+C17 -> 255000 | E15: 85% do faturamento; geram crédito de IBS/CBS no híbrido
B16: → das quais, compras de fornecedores Lucro Real/Presumido | C16: 178500 | E16: 70% das compras com crédito cheio
B17: → das quais, compras de outros optantes do Simples | C17: 76500 | E17: 30% sem crédito cheio (transição)
B18: Folha de pagamento (salários) | C18: 22000 | E18: 8 funcionários — não gera crédito IBS/CBS
B19: Encargos s/ folha (FGTS, etc. 12%) | C19: =C18*0.12 -> 2640 | E19: Estimativa de encargos do Simples
B20: Pró-labore sócios | C20: 8000 | E20: Não gera crédito
B21: Aluguel galpão/loja | C21: 9000 | E21: Gera crédito IBS/CBS no híbrido
B22: Energia, água, telecom | C22: 4500 | E22: Gera crédito IBS/CBS no híbrido
B23: Frete e logística | C23: 6000 | E23: Gera crédito IBS/CBS no híbrido
B24: Outras despesas operacionais | C24: 5000 | E24: Material, software, manutenção
B26: 3. PARÂMETROS TRIBUTÁRIOS
B28: Alíquota efetiva atual do Simples (Anexo I, faixa RBT12) | C28: 0.1187 | E28: Sobre RBT12 R$3,6mi → alíquota efetiva do Anexo I
B29: → parcela de PIS/COFINS dentro do DAS atual | C29: 0.0184 | E29: repartição PIS+COFINS do Anexo I
B30: → parcela de ICMS dentro do DAS atual | C30: 0.0397 | E30: repartição ICMS do Anexo I
B31: Crédito PIS/COFINS que o cliente toma HOJE | C31: 0.0365 | E31: Crédito cheio na nota, regra atual
B32: Alíquota cheia IBS+CBS (regime regular / referência) | C32: 0.265 | E32: IVA dual de referência 26,5%
B33: → CBS (federal) | C33: 0.088 | E33: Componente federal
B34: → IBS (estadual+municipal) | C34: 0.177 | E34: Componente subnacional
B35: IBS/CBS embutido no DAS (regime unificado) | C35: 0.0184 | E35: Crédito reduzido que o cliente recebe se ficar no DAS
B37: NOTA METODOLÓGICA: valores tributários são parâmetros de referência da transição da LC 214/2025 (IBS/CBS plenos a partir de 2033; alíquota de referência 26,5%). As alíquotas efetivas do Simples e a repartição por tributo dependem da faixa do RBT12 e devem ser confirmadas no PGDAS. Dados de despesas/folha são fictícios.

Sheet Carga Tributária Empresa
B2: CARGA TRIBUTÁRIA DA EMPRESA — 3 Cenários (mensal)
B4: Linha | C4: DAS atual (hoje) | D4: Unificado (DAS) | E4: HÍBRIDO (por fora)
B5: Receita bruta mensal | C5: =Premissas!$C$7 -> 300000 | D5: =Premissas!$C$7 -> 300000 | E5: =Premissas!$C$7 -> 300000
B7: DAS — Simples (alíq. efetiva total) | C7: =Premissas!$C$7*Premissas!$C$28 -> 35610
B8: DAS — Simples (mantém integral) | D8: =Premissas!$C$7*Premissas!$C$28 -> 35610
B9: DAS — Simples REDUZIDO (sai parc. ICMS+PIS/COFINS) | E9: =Premissas!$C$7*(Premissas!$C$28-Premissas!$C$29-Premissas!$C$30) -> 18180
B11: IBS/CBS débito (sobre vendas) | E11: =Premissas!$C$7*Premissas!$C$32 -> 79500
B12: (-) Crédito IBS/CBS sobre compras tributadas | E12: =-(Premissas!C16+Premissas!C21+Premissas!C22+Premissas!C23)*Premissas!$C$32 -> -52470
B13: IBS/CBS líquido a recolher (por fora) | E13: =E11+E12 -> 27030
B15: CARGA TRIBUTÁRIA TOTAL DA EMPRESA | C15: =C7 -> 35610 | D15: =D8 -> 35610 | E15: =E9+E13 -> 45210
B16: Carga sobre faturamento | C16: =C15/C5 -> 0.1187 | D16: =D15/D5 -> 0.1187 | E16: =E15/E5 -> 0.1507
B18: Crédito transferido ao CLIENTE Lucro Real (por R$100 de venda)
B19: Crédito que o cliente recebe | C19: =Premissas!$C$31*100 -> 3.65 | D19: =Premissas!$C$35*100 -> 1.84 | E19: =Premissas!$C$32*100 -> 26.5
B21: LEITURA: no regime UNIFICADO a carga própria da empresa quase não muda, mas o crédito ao cliente despenca (vermelho) → risco comercial. No HÍBRIDO a empresa passa a recolher IBS/CBS por fora (com créditos das compras), o DAS é reduzido, e o cliente recebe crédito cheio (verde). O ganho líquido depende de quanto da carteira B2B se credita (80% neste case) e do volume de compras com crédito.

Sheet Impacto Cliente
B2: IMPACTO NO CLIENTE LUCRO REAL — Perda de Crédito
B4: Crédito tributário que o varejista Lucro Real recebe a cada R$100 comprados
B6: Cenário | C6: Base (compra) | D6: Crédito recebido | E6: % sobre compra
B7: HOJE — crédito PIS/COFINS presumido (9,25%) | C7: 100 | D7: =C7*Premissas!$C$31 -> 3.65 | E7: =D7/C7 -> 0.0365
B8: REFORMA — Simples no DAS (crédito reduzido) | C8: 100 | D8: =C8*Premissas!$C$35 -> 1.84 | E8: =D8/C8 -> 0.0184
B9: REFORMA — Simples HÍBRIDO (crédito cheio IBS/CBS) | C9: 100 | D9: =C9*Premissas!$C$32 -> 26.5 | E9: =D9/C9 -> 0.265
B11: Conclusão a/ cliente:
B12: Se o atacadista permanecer no DAS, o cliente Lucro Real deixa de tomar 9,25% e passa a tomar apenas 1,1% de crédito — uma perda de 8 pontos sobre o valor da compra. Para neutralizar, o cliente exigirá desconto equivalente, ou trocará de fornecedor por um do regime regular. No regime HÍBRIDO, o crédito sobe para 26,5% (cheio), tornando o atacadista MAIS competitivo que hoje perante clientes que se creditam.

Sheet Passo DAS 2027
B2: PASSO A PASSO — TUDO DENTRO DO SIMPLES (DAS) · 2027
B4: Cálculo do DAS — Anexo I, com IBS/CBS embutidos na guia única
B6: 1 | C6: Receita bruta mensal | D6: =Premissas!$C$7 -> 300000 | E6: Faturamento do mês
B7: 2 | C7: RBT12 (receita acumulada 12 meses) | D7: =Premissas!$C$8 -> 3600000 | E7: RBT12 = receita do mês vezes 12
B8: 3 | C8: Alíquota nominal da faixa (Anexo I) | D8: 0.143 | E8: 3ª faixa: nominal 10,5%
B9: 4 | C9: Parcela a deduzir (PD) da faixa | D9: 87300 | E9: PD da 3ª faixa do Anexo I
B10: 5 | C10: Alíquota EFETIVA = (RBT12×nominal − PD)/RBT12 | D10: =(D7*D8-D9)/D7 -> 0.11875 | E10: Fórmula oficial do Simples
B11: 6 | C11: DAS total do mês = receita × alíq. efetiva | D11: =D6*D10 -> 35625 | E11: Guia única — inclui tudo
B13: Como o DAS se reparte (e quanto de crédito o cliente recebe)
B15: 7 | C15: parcela ICMS embutida no DAS | D15: 10200 | E15: Permanece no Simples em 2027
B16: 8 | C16: parcela CBS/IBS embutida no DAS (regime unificado) | D16: =Premissas!$C$35*D6 -> 5520 | E16: IBS/CBS embutido 1,1% (baixo)
B17: 9 | C17: CRÉDITO de IBS/CBS transferido ao cliente | D17: =D16 -> 5520 | E17: crédito = só o IBS/CBS embutido no DAS
B18: 10 | C18: Crédito por R$100 vendidos ao cliente | D18: =D17/D6*100 -> 1.84 | E18: ≈ R$1,84 — perda vs. 9,25% de hoje
B20: RESUMO (DAS 2027): a empresa recolhe TUDO numa guia (R$ do passo 6). Simples administrativamente, mas o cliente Lucro Real recebe crédito de IBS/CBS irrisório (1,1%, passo 9-10). Para um atacadista B2B isso destrói competitividade, pois o concorrente do regime regular entrega crédito cheio.

Sheet Passo Híbrido 2027
B2: PASSO A PASSO — REGIME HÍBRIDO (IBS/CBS POR FORA) · 2027
B4: Parte 1 — Recomposição do DAS: TIRA PIS/COFINS e RETIRA também o IBS/CBS para apuração própria
B5: Base legal: LC 214/2025, art. 41 (opção do optante do Simples por apurar IBS/CBS no regime regular, por fora do DAS) c/c art. 344 (alíquotas de transição 2027/2028).
B6: 1 | C6: Receita bruta mensal | D6: =Premissas!$C$7 -> 300000 | E6: Faturamento do mês
B7: 2 | C7: DAS cheio do regime unificado (alíq. efetiva) | D7: ='Passo DAS 2027'!D11 -> 35625 | E7: Ponto de partida = guia única normal
B8: 3 | C8: (-) PIS/COFINS embutido no DAS → vira CBS | D8: =-'Passo DAS 2027'!D16 -> -5520 | E8: PIS/COFINS extintos em 2027 (art.344). Sai do DAS
B9: 4 | C9: (-) IBS/CBS embutido no DAS (regime unificado) | D9: =-'Passo DAS 2027'!D16 -> -5520 | E9: Retirado: passa a ser apurado POR FORA (art.41)
B10: 5 | C10: DAS REDUZIDO a recolher (ICMS+CPP+IRPJ+CSLL) | D10: =D7+D8+D9 -> 24585 | E10: Em 2027 ICMS permanece no DAS
B12: Parte 2 — ADICIONA IBS/CBS apurado POR FORA (regime regular, não cumulativo)
B13: Base legal: LC 214/2025, art. 41 (apuração regular por débito e crédito) e art. 344 (CBS ref. 8,8% reduzida 0,1pp + IBS 0,1% em 2027). PIS/COFINS já extinto (art. 343/344).
B14: 6 | C14: DÉBITO — IBS/CBS sobre as vendas | D14: =D6*0.088 -> 26400 | E14: Receita × (CBS 8,7% + IBS 0,1%)
B15: 7 | C15: Base de crédito — compras/insumos tributados | D15: =Premissas!C16+Premissas!C21+Premissas!C22+Premissas!C23 -> 198000 | E15: Compras LR + aluguel + energia + frete
B16: 8 | C16: (-) CRÉDITO — IBS/CBS das compras | D16: =-D15*0.088 -> -17424 | E16: Não cumulatividade plena
B17: 9 | C17: IBS/CBS LÍQUIDO a recolher POR FORA | D17: =D14+D16 -> 8976 | E17: Débito − crédito
B19: Parte 3 — Carga total da empresa e crédito ao cliente
B21: 10 | C21: CARGA TOTAL 2027 = DAS reduzido + IBS/CBS por fora | D21: =D10+D17 -> 33561 | E21: Soma dos dois recolhimentos
B22: 11 | C22: CRÉDITO de IBS/CBS transferido ao cliente (cheio) | D22: =D14 -> 26400 | E22: crédito = débito integral destacado na NF
B23: 12 | C23: Crédito por R$100 vendidos ao cliente | D23: =D22/D6*100 -> 8.8 | E23: ≈ R$8,80 — vs. R$1,10 no DAS
B25: Comparativo direto 2027 — mesma empresa, mesmo mês
B27: Indicador | C27: DENTRO do Simples (DAS) | D27: HÍBRIDO (por fora) | E27: Diferença
B28: Carga tributária da empresa | C28: ='Passo DAS 2027'!D11 -> 35625 | D28: =D21 -> 33561 | E28: =D28-C28 -> -2064
B29: Crédito ao cliente (por R$100) | C29: ='Passo DAS 2027'!D18 -> 1.84 | D29: =D23 -> 8.8 | E29: =D29-C29 -> 6.96
B31: MECÂNICA CORRETA DA PARTE 1: o DAS cheio (passo 2) tem dois componentes que SAEM no híbrido — a parcela federal PIS/COFINS, que em 2027 é extinta e dá lugar à CBS (art.344), e a parcela de IBS/CBS que estava embutida no regime unificado (passo 4). Ambas saem do DAS; o que sobra na guia (passo 5) são ICMS, CPP, IRPJ e CSLL — pois em 2027 o ICMS vive dentro do Simples (só migra de 2029 a 2033). Em seguida, o IBS/CBS é RECOLOCADO na Parte 2, agora apurado por fora pela sistemática regular de débito e crédito (art. 41 da LC 214/2025), gerando crédito CHEIO ao cliente. Resultado: pequena diferença de carga, mas crédito ~8x maior ao cliente Lucro Real. Números fictícios; confirmar faixa no PGDAS.

Sheet Desconto Atacadista
B2: O DESCONTO QUE O ATACADISTA TERIA QUE DAR — imposto por dentro × por fora
B4: Conceito: o imposto deixa de ser POR DENTRO (embutido no preço) e passa a ser POR FORA (destacado por cima)
B5: Hoje, ICMS/PIS/COFINS estão EMBUTIDOS no preço da mercadoria (cálculo 'por dentro'): o cliente paga um preço único e o crédito vem presumido na nota. Com a reforma, o IBS/CBS é 'por fora': calculado sobre o valor líquido e DESTACADO por cima do preço, como um adicional. O cliente paga preço + IBS/CBS, mas credita o IBS/CBS integralmente — então o custo que de fato 'fica' para ele é só o valor líquido da mercadoria. É por isso que o que importa na negociação é o CUSTO LÍQUIDO do cliente.
B9: Premissas da operação (por R$100 de mercadoria)
B10: 1 | C10: Preço da mercadoria (valor líquido base) | D10: 100 | E10: Base de referência para a conta
B11: 2 | C11: Crédito que o cliente toma HOJE (PIS/COFINS 9,25%) | D11: =D10*Premissas!$C$31 -> 3.65 | E11: Crédito presumido embutido
B12: 3 | C12: Crédito no DAS (reforma, unificado ~1,1%) | D12: =D10*Premissas!$C$35 -> 1.84 | E12: Crédito reduzido
B13: 4 | C13: Crédito no HÍBRIDO (IBS/CBS por fora, 8,8% em 2027) | D13: =D10*0.088 -> 8.8 | E13: Crédito cheio destacado
B15: Cenário de referência — o custo líquido do cliente HOJE
B16: 5 | C16: Preço pago hoje (imposto por dentro) | D16: =D10 -> 100 | E16: Preço único, tributo embutido
B17: 6 | C17: (-) Crédito recuperado hoje | D17: =-D11 -> -3.65 | E17: PIS/COFINS presumido
B18: 7 | C18: → Custo líquido do cliente HOJE | D18: =D16+D17 -> 96.35 | E18: Inclui crédito presumido 'inflado' do sistema atual
B20: Se o atacadista FICAR no DAS e NÃO der desconto — o cliente perde
B21: 8 | C21: Preço pago (mesmo de hoje) | D21: =D10 -> 100 | E21: Atacadista mantém preço
B22: 9 | C22: (-) Crédito recuperado no DAS | D22: =-D12 -> -1.84 | E22: Só 1,1%
B23: 10 | C23: → Custo líquido do cliente | D23: =D21+D22 -> 98.16 | E23: Subiu!
B24: 11 | C24: SOBRECUSTO para o cliente vs. hoje | D24: =D23-D18 -> 1.81 | E24: Quanto o cliente perde por R$100
B26: Quanto de DESCONTO o atacadista no DAS teria que dar para neutralizar a perda
B27: 12 | C27: Preço de equilíbrio (custo líq. cliente = hoje) | D27: =D18-D22 -> 98.19 | E27: Preço tal que custo líquido volta ao de hoje
B28: 13 | C28: DESCONTO necessário (R$ por R$100) | D28: =D10-D27 -> 1.81 | E28: Quanto o preço precisa cair
B29: 14 | C29: DESCONTO necessário (%) | D29: =D28/D10 -> 0.0181 | E29: % de desconto no preço
B30: 15 | C30: Margem bruta atual do atacadista | D30: =Premissas!$C$11 -> 0.15 | E30: Para comparar com o desconto
B31: 16 | C31: Desconto consome desta fatia da margem | D31: =D29/Premissas!$C$11 -> 0.12066667 | E31: % da margem que o desconto devora
B33: Se o atacadista vai para o HÍBRIDO — sem precisar de desconto
B34: 17 | C34: Preço líquido da mercadoria | D34: =D10 -> 100 | E34: Mesmo valor base
B35: 18 | C35: (+) IBS/CBS destacado POR FORA | D35: =D13 -> 8.8 | E35: Adicionado por cima na nota
B36: 19 | C36: Preço total na nota (o cliente desembolsa) | D36: =D34+D35 -> 108.8 | E36: Preço + imposto por fora
B37: 20 | C37: (-) Crédito cheio de IBS/CBS recuperado | D37: =-D13 -> -8.8 | E37: Cliente credita 100% do destacado
B38: 21 | C38: → Custo líquido do cliente no HÍBRIDO | D38: =D36+D37 -> 100 | E38: Volta a ser só a mercadoria
B39: 22 | C39: Custo líquido vs. concorrente do regime regular | D39: =D38-D34 -> 0 | E39: Empata com o concorrente: SEM desconto necessário
B41: CONCLUSÃO COMERCIAL: o crédito de 9,25% de hoje é em parte ARTIFICIAL — o cliente credita mais do que o atacadista do Simples efetivamente paga. A reforma encerra esse benefício para todos. O que o atacadista controla é a COMPARAÇÃO COM O CONCORRENTE: se ficar no DAS, entrega só 1,1% de crédito e fica em desvantagem — para empatar com um concorrente do regime regular precisaria dar 8% de desconto, devorando 54% da margem (passos 13 a 16). No HÍBRIDO, o IBS/CBS é destacado POR FORA e o cliente credita 100%: o custo líquido do cliente é só a mercadoria, igual ao do concorrente regular — SEM desconto e SEM corroer margem (passos 17 a 22). Tudo por R$100 de mercadoria; ajuste o preço base (amarelo) e alíquotas na aba Premissas. Dados fictícios.
