Workbook

Sheet Simples Nacional (ref.)
A1: FATURAMENTO E TRIBUTOS 2025 — ENQUADRAMENTO ATUAL: SIMPLES NACIONAL (dados de origem)
A3: Mês | B3: Jan | C3: Fev | D3: Mar | E3: Abr | F3: Mai | G3: Jun | H3: Jul | I3: Ago | J3: Set | K3: Out | L3: Nov | M3: Dez | N3: Total
A4: Faturamento | B4: 10 | C4: 10 | D4: 10 | E4: 10 | F4: 10 | G4: 10 | H4: 10 | I4: 10 | J4: 10 | K4: 10 | L4: 10 | M4: 10 | N4: =SUM(B4:M4) -> 120
A5: Alíquota efetiva DAS (%) | B5: 0.14895287 | C5: 0.14764293 | D5: 0.1500255 | E5: 0.14346148 | F5: 0.10094318 | G5: 0.15262019 | H5: 0.099172496 | I5: 0.09842604 | J5: 0.09889473 | K5: 0.09959295 | L5: 0.09512286 | M5: 0.09106189 | N5: dado original
A6: Imposto DAS (Simples) | B6: =B4*B5 -> 1.4895287 | C6: =C4*C5 -> 1.4764293 | D6: =D4*D5 -> 1.500255 | E6: =E4*E5 -> 1.4346148 | F6: =F4*F5 -> 1.0094318 | G6: =G4*G5 -> 1.5262019 | H6: =H4*H5 -> 0.99172496 | I6: =I4*I5 -> 0.9842604 | ... M6: =M4*M5 -> 0.9106189 | N6: =SUM(B6:M6) -> 14.259171
A8: TOTAL DE TRIBUTOS PAGOS NO SIMPLES NACIONAL (2025) | N8: =N6 -> 14.259171
A10: Observação: a alíquota efetiva do DAS já engloba, de forma unificada, IRPJ, CSLL, PIS, COFINS, CPP (INSS Patronal), ISS e/ou ICMS,
A11: conforme o Anexo do Simples Nacional em que a empresa está enquadrada. Anexo IV)

Sheet Lucro Presumido (simulação)
A1: SIMULAÇÃO — TRIBUTOS NO REGIME DE LUCRO PRESUMIDO (2025)
A3: PARÂMETROS E ALÍQUOTAS ADOTADAS
A4: Percentual de presunção — IRPJ (serviços em geral) | D4: 0.32
A5: Percentual de presunção — CSLL (serviços em geral) | D5: 0.32
A6: Alíquota IRPJ (sobre a base presumida) | D6: 0.15
A7: Adicional de IRPJ (sobre parcela que exceder o limite trimestral) | D7: 0.1
A8: Limite trimestral para incidência do adicional (R$ 20.000/mês x 3) | D8: 60000
A9: Alíquota CSLL (sobre a base presumida) | D9: 0.09
A10: Alíquota PIS (regime cumulativo) | D10: 0.0065
A11: Alíquota COFINS (regime cumulativo) | D11: 0.03
A12: Alíquota ISS (município — mesma alíquota já utilizada na planilha original) | D12: 0.05
A13: Folha de pagamento mensal estimada (preencher para calcular INSS Patronal) | D13: 0
A14: Alíquota INSS Patronal (CPP) sobre a folha | D14: 0.2
A16: Células em amarelo são premissas/parâmetros editáveis. Ajuste conforme a atividade real (CNAE) e o município da empresa.
A18: APURAÇÃO MENSAL (PIS, COFINS, ISS, INSS PATRONAL)
A19: Mês | B19: Jan | C19: Fev | D19: Mar | E19: Abr | F19: Mai | G19: Jun | H19: Jul | I19: Ago | J19: Set | K19: Out | L19: Nov | M19: Dez | N19: Total
A20: Faturamento | B20: ='Simples Nacional (ref.)'!B4 -> 10 | C20: ='Simples Nacional (ref.)'!C4 -> 10 | D20: ='Simples Nacional (ref.)'!D4 -> 10 | E20: ='Simples Nacional (ref.)'!E4 -> 10 | F20: ='Simples Nacional (ref.)'!F4 -> 10 | G20: ='Simples Nacional (ref.)'!G4 -> 10 | H20: ='Simples Nacional (ref.)'!H4 -> 10 | I20: ='Simples Nacional (ref.)'!I4 -> 10 | ... M20: ='Simples Nacional (ref.)'!M4 -> 10 | N20: =SUM(B20:M20) -> 120
A21: PIS (cumulativo) | B21: =B20*$D$10 -> 0.065 | C21: =C20*$D$10 -> 0.065 | D21: =D20*$D$10 -> 0.065 | E21: =E20*$D$10 -> 0.065 | F21: =F20*$D$10 -> 0.065 | G21: =G20*$D$10 -> 0.065 | H21: =H20*$D$10 -> 0.065 | I21: =I20*$D$10 -> 0.065 | ... M21: =M20*$D$10 -> 0.065 | N21: =SUM(B21:M21) -> 0.78
A22: COFINS (cumulativo) | B22: =B20*$D$11 -> 0.3 | C22: =C20*$D$11 -> 0.3 | D22: =D20*$D$11 -> 0.3 | E22: =E20*$D$11 -> 0.3 | F22: =F20*$D$11 -> 0.3 | G22: =G20*$D$11 -> 0.3 | H22: =H20*$D$11 -> 0.3 | I22: =I20*$D$11 -> 0.3 | ... M22: =M20*$D$11 -> 0.3 | N22: =SUM(B22:M22) -> 3.6
A23: ISS | B23: =B20*$D$12 -> 0.5 | C23: =C20*$D$12 -> 0.5 | D23: =D20*$D$12 -> 0.5 | E23: =E20*$D$12 -> 0.5 | F23: =F20*$D$12 -> 0.5 | G23: =G20*$D$12 -> 0.5 | H23: =H20*$D$12 -> 0.5 | I23: =I20*$D$12 -> 0.5 | ... M23: =M20*$D$12 -> 0.5 | N23: =SUM(B23:M23) -> 6
A24: Subtotal mensal (PIS+COFINS+ISS+CPP) | B24: =SUM(B21:B23) -> 0.865 | C24: =SUM(C21:C23) -> 0.865 | D24: =SUM(D21:D23) -> 0.865 | E24: =SUM(E21:E23) -> 0.865 | F24: =SUM(F21:F23) -> 0.865 | G24: =SUM(G21:G23) -> 0.865 | H24: =SUM(H21:H23) -> 0.865 | I24: =SUM(I21:I23) -> 0.865 | ... M24: =SUM(M21:M23) -> 0.865 | N24: =SUM(B24:M24) -> 10.38
A26: APURAÇÃO TRIMESTRAL — IRPJ E CSLL (apuração legal trimestral no Lucro Presumido)
A27: Trimestre | B27: Período | C27: Receita do Trimestre | D27: Base Presunção IRPJ (32%) | E27: IRPJ (15%) | F27: Parcela Excedente ao Limite | G27: Adicional IRPJ (10%) | H27: IRPJ Total | I27: Base Presunção CSLL (32%) | J27: CSLL (9%)
A28: 1º Trimestre | B28: Jan-Mar | C28: =SUM(B20:D20) -> 30 | D28: =C28*$D$4 -> 9.6 | E28: =D28*$D$6 -> 1.44 | F28: =MAX(D28-$D$8,0) -> 0 | G28: =F28*$D$7 -> 0 | H28: =E28+G28 -> 1.44 | I28: =C28*$D$5 -> 9.6 | J28: =I28*$D$9 -> 0.864
A29: 2º Trimestre | B29: Abr-Jun | C29: =SUM(E20:G20) -> 30 | D29: =C29*$D$4 -> 9.6 | E29: =D29*$D$6 -> 1.44 | F29: =MAX(D29-$D$8,0) -> 0 | G29: =F29*$D$7 -> 0 | H29: =E29+G29 -> 1.44 | I29: =C29*$D$5 -> 9.6 | J29: =I29*$D$9 -> 0.864
A30: 3º Trimestre | B30: Jul-Set | C30: =SUM(H20:J20) -> 30 | D30: =C30*$D$4 -> 9.6 | E30: =D30*$D$6 -> 1.44 | F30: =MAX(D30-$D$8,0) -> 0 | G30: =F30*$D$7 -> 0 | H30: =E30+G30 -> 1.44 | I30: =C30*$D$5 -> 9.6 | J30: =I30*$D$9 -> 0.864
A31: 4º Trimestre | B31: Out-Dez | C31: =SUM(K20:M20) -> 30 | D31: =C31*$D$4 -> 9.6 | E31: =D31*$D$6 -> 1.44 | F31: =MAX(D31-$D$8,0) -> 0 | G31: =F31*$D$7 -> 0 | H31: =E31+G31 -> 1.44 | I31: =C31*$D$5 -> 9.6 | J31: =I31*$D$9 -> 0.864
A32: Total Anual | C32: =SUM(C28:C31) -> 120 | D32: =SUM(D28:D31) -> 38.4 | E32: =SUM(E28:E31) -> 5.76 | F32: =SUM(F28:F31) -> 0 | G32: =SUM(G28:G31) -> 0 | H32: =SUM(H28:H31) -> 5.76 | I32: =SUM(I28:I31) -> 38.4 | J32: =SUM(J28:J31) -> 3.456
A33: IRPJ e CSLL são apurados trimestralmente por determinação legal (diferente de PIS/COFINS/ISS, que são mensais).
A35: TOTAL ANUAL DE TRIBUTOS — LUCRO PRESUMIDO
A36: PIS | C36: =N21 -> 0.78
A37: COFINS | C37: =N22 -> 3.6
A38: ISS | C38: =N23 -> 6
A39: IRPJ (inclui adicional) | C39: =H32 -> 5.76
A40: CSLL | C40: =J32 -> 3.456
A41: TOTAL GERAL — LUCRO PRESUMIDO | C41: =SUM(C36:C40) -> 19.596
A43: • Atividade não informada: foi adotado o percentual de presunção de 32% (IRPJ e CSLL) • PIS/COFINS calculados pelo regime cumulativo (0,65% e 3%), padrão do Lucro Presumido. • ISS calculado a 5%, mesma alíquota já utilizada na planilha original do Simples Nacional — confirmar a alíquota vigente no município.

Sheet Comparativo
A1: COMPARATIVO — SIMPLES NACIONAL x LUCRO PRESUMIDO (2025)
A3: Regime Tributário | B3: Total Anual de Tributos
A4: Simples Nacional (regime atual) | B4: ='Simples Nacional (ref.)'!N8 -> 14.259171
A5: Lucro Presumido (simulado) | B5: ='Lucro Presumido (simulação)'!C41 -> 19.596
A6: Diferença (R$) | B6: =B5-B4 -> 5.3368289
A7: Diferença (%) | B7: =B6/B4 -> 0.37427343
A9: Carga tributária efetiva sobre o faturamento
A10: Simples Nacional | B10: =B4/'Simples Nacional (ref.)'!N4 -> 0.11882643
A11: Lucro Presumido | B11: =B5/'Lucro Presumido (simulação)'!N20 -> 0.1633
A13: CONCLUSÃO DA SIMULAÇÃO: Com base no faturamento apurado (Jan a Ago/2026) e nas premissas descritas na aba 'Lucro Presumido (simulação)', a migração para o Lucro Presumido resultaria em carga tributária SUPERIOR à do Simples Nacional. Isso ocorre principalmente porque, no Lucro Presumido, o ISS passa a ser recolhido à parte (5%) e a soma de IRPJ + CSLL sobre a presunção de 32% tende a superar o que era pago de forma unificada no DAS.

Sheet Dashboard
A1: DASHBOARD TRIBUTÁRIO — SIMPLES NACIONAL x LUCRO PRESUMIDO
A4: Ano-base 2025 | Faturamento apurado de Jan a Ago |
A6: FATURAMENTO TOTAL (2025) | D6: TOTAL — SIMPLES NACIONAL | G6: TOTAL — LUCRO PRESUMIDO | J6: DIFERENÇA (LP vs SIMPLES)
A7: ='Lucro Presumido (simulação)'!N20 -> 120 | D7: =Comparativo!B4 -> 14.259171 | G7: =Comparativo!B5 -> 19.596 | J7: =Comparativo!B6 -> 5.3368289
A9: DIFERENÇA (%) | D9: CARGA EFETIVA — SIMPLES | G9: CARGA EFETIVA — LUCRO PRES. | J9: REGIME MAIS VANTAJOSO
A10: =Comparativo!B7 -> 0.37427343 | D10: =Comparativo!B10 -> 0.11882643 | G10: =Comparativo!B11 -> 0.1633 | J10: =IF(Comparativo!B6>0,"SIMPLES NACIONAL","LUCRO PRESUMIDO") -> SIMPLES NACIONAL
A12: 📈 Evolução do Faturamento Mensal (2025) | G12: ⚖️ Simples Nacional x Lucro Presumido — Total Anual
A30: 🥧 Composição dos Tributos — Lucro Presumido | G30: 📊 IRPJ + CSLL por Trimestre — Lucro Presumido
A48: ⚠ PREMISSAS DA SIMULAÇÃO: presunção de 32% (IRPJ/CSLL) para 'serviços em geral' — ajustar conforme o CNAE real da empresa; PIS 0,65% e COFINS 3% no regime cumulativo; ISS a 5% (mesma alíquota da planilha original).
